photerr/__init__.py
photerr/euclid.py
photerr/lsstV1.py
photerr/lsstV2.py
photerr/model.py
photerr/params.py
photerr/roman.py
photerr-1.4.0.dist-info/LICENSE
photerr-1.4.0.dist-info/METADATA
photerr-1.4.0.dist-info/WHEEL
photerr-1.4.0.dist-info/RECORD
