Metadata-Version: 2.3
Name: photerr
Version: 1.4.0
Summary: Photometric error model for astronomical imaging surveys
Author: John Franklin Crenshaw
Author-email: jfcrenshaw@gmail.com
Requires-Python: >=3.10,<4.0
Classifier: Programming Language :: Python :: 3
Classifier: Programming Language :: Python :: 3.10
Classifier: Programming Language :: Python :: 3.11
Classifier: Programming Language :: Python :: 3.12
Classifier: Programming Language :: Python :: 3.13
Requires-Dist: numpy (>=1.23.2)
Requires-Dist: pandas (>=1.4.3)
Project-URL: Homepage, https://github.com/jfcrenshaw/photerr
